middlewares.py
scrapy_accessory/__init__.py
scrapy_accessory/feedexporter.py
scrapy_accessory/middlewares.py
scrapy_accessory/pipelines.py
scrapy_accessory-0.2.1.dist-info/METADATA
scrapy_accessory-0.2.1.dist-info/WHEEL
scrapy_accessory-0.2.1.dist-info/top_level.txt
scrapy_accessory-0.2.1.dist-info/RECORD
