Metadata-Version: 2.1
Name: scrapy-accessory
Version: 0.2.1
Summary: A simple accessory tools for Scrapy.
Home-page: UNKNOWN
Author: wuwentao
Author-email: wwtg99@126.com
License: BSD
Keywords: scrapy middleware
Platform: any
Classifier: Environment :: Web Environment
Classifier: Intended Audience :: Developers
Classifier: License :: OSI Approved :: BSD License
Classifier: Operating System :: OS Independent
Classifier: Programming Language :: Python
Classifier: Programming Language :: Python :: 3
Classifier: Programming Language :: Python :: 3.4
Classifier: Programming Language :: Python :: 3.5
Classifier: Programming Language :: Python :: 3.6
Classifier: Programming Language :: Python :: 3.7
Classifier: Programming Language :: Python :: 3.8
Classifier: Topic :: Software Development :: Libraries :: Python Modules
Requires-Python: >=3.4
Requires-Dist: scrapy (>=1.7)
